Metadata-Version: 2.1
Name: instapy-mad
Version: 0.6.14
Summary: Tool for automated Instagram interactions
Home-page: https://github.com/timgrossmann/InstaPy
Author: Tim Großmann
Author-email: contact.timgrossmann@gmail.com
Maintainer: InstaPy Community at Github
License: GPLv3
Download-URL: https://github.com/timgrossmann/InstaPy/archive/master.zip
Project-URL: How Tos, https://github.com/timgrossmann/InstaPy/tree/master/docs
Project-URL: Examples, https://github.com/timgrossmann/InstaPy/tree/master/quickstart_templates
Project-URL: Bug Reports, https://github.com/timgrossmann/InstaPy/issues
Project-URL: Funding, https://www.paypal.me/supportInstaPy
Project-URL: Say Thanks!, http://saythanks.io/to/uluQulu
Project-URL: Source, https://github.com/timgrossmann/InstaPy/tree/master/instapy
Keywords: instapy python instagram automation          marketing promotion bot selenium
Platform: win32
Platform: linux
Platform: linux2
Platform: darwin
Classifier: Development Status :: 4 - Beta
Classifier: Environment :: Console
Classifier: Environment :: Win32 (MS Windows)
Classifier: Environment :: MacOS X
Classifier: Environment :: Web Environment
Classifier: Intended Audience :: End Users/Desktop
Classifier: Intended Audience :: Developers
Classifier: Operating System :: Microsoft :: Windows
Classifier: Operating System :: POSIX :: Linux
Classifier: Operating System :: MacOS :: MacOS X
Classifier: Operating System :: Unix
Classifier: Programming Language :: Python
Classifier: Programming Language :: JavaScript
Classifier: Programming Language :: SQL
Classifier: Topic :: Utilities
Classifier: Topic :: Software Development :: Build Tools
Classifier: Programming Language :: Python :: 3
Classifier: Programming Language :: Python :: 3.4
Classifier: Programming Language :: Python :: 3.5
Classifier: Programming Language :: Python :: 3.6
Classifier: Programming Language :: Python :: 3.7
Classifier: Natural Language :: English
Requires-Python: >=3, !=3.0.*, !=3.1.*, !=3.2.*, !=3.3.*
Requires-Dist: EasyProcess (>=0.2.3)
Requires-Dist: MeaningCloud-python (>=1.1.1)
Requires-Dist: PyYAML (>=3.13)
Requires-Dist: certifi (>=2018.10.15)
Requires-Dist: chardet (<4,>=3.0.4)
Requires-Dist: clarifai (>=2.4.1)
Requires-Dist: configparser (<4,>=3.5.0)
Requires-Dist: emoji (>=0.5.1)
Requires-Dist: future (>=0.17.1)
Requires-Dist: grpcio (>=1.16.1)
Requires-Dist: idna (<3,>=2.7)
Requires-Dist: jsonschema (<3,>=2.6.0)
Requires-Dist: plyer (>=1.3.1)
Requires-Dist: protobuf (<4,>=3.6.1)
Requires-Dist: regex (>=2018.11.22)
Requires-Dist: requests (>=2.20.1)
Requires-Dist: selenium (>=3.141.0)
Requires-Dist: setuptools-rust (>=0.11.6)
Requires-Dist: six (>=1.11.0)
Requires-Dist: urllib3 (>=1.24.1)
Requires-Dist: webdriverdownloader (>=1.1.0.3)
Requires-Dist: api-display-purposes (>=0.0.3) ; python_version > "3.5"
Requires-Dist: python-telegram-bot (>=12.0.0) ; python_version > "3.6"
Requires-Dist: PyVirtualDisplay (>=0.2.1) ; sys_platform != "win32"
Provides-Extra: test
Requires-Dist: tox ; extra == 'test'
Requires-Dist: tox-venv ; extra == 'test'
Requires-Dist: virtualenv ; extra == 'test'
